README.md
pyproject.toml
email_hunter/__init__.py
email_hunter/cli.py
email_hunter.egg-info/PKG-INFO
email_hunter.egg-info/SOURCES.txt
email_hunter.egg-info/dependency_links.txt
email_hunter.egg-info/entry_points.txt
email_hunter.egg-info/requires.txt
email_hunter.egg-info/top_level.txt
email_hunter/utils/__init__.py
email_hunter/utils/colors.py
email_hunter/utils/fortunes.py
email_hunter/verifiers/__init__.py
email_hunter/verifiers/cve_2023_23397.py