Metadata-Version: 2.1
Name: email-hunter
Version: 0.1.0
Summary: Another package to analyse emails to find potential threats.
Author-email: Félix Brezo <contacto@felixbrezo.com>
License: GNU GPLv3+
Project-URL: Homepage, https://github.com/febrezo/email-hunter
Project-URL: Bug Tracker, https://github.com/febrezo/email-hunter/issues
Keywords: threat-hunting,dfir,forensics,email,cve-2023-23397
Classifier: Programming Language :: Python :: 3
Classifier: License :: OSI Approved :: GNU General Public License v3 or later (GPLv3+)
Classifier: Operating System :: OS Independent
Classifier: Development Status :: 5 - Production/Stable
Classifier: Topic :: Security
Classifier: Topic :: Communications :: Email
Requires-Python: >=3.7
